{
  "variants": {
    "full=true": [
      {
        "model": "end_aspected:block/void"
      },
      {
        "model": "end_aspected:block/void_mirrored"
      },
      {
        "model": "end_aspected:block/void",
        "y": 180
      },
      {
        "model": "end_aspected:block/void_mirrored",
        "y": 180
      }
    ],
    "full=false": [
      { "model": "end_aspected:block/void_empty" },
      { "model": "end_aspected:block/void_empty", "x": 180 },
      { "model": "end_aspected:block/void_empty", "x": 180, "y": 180 },
      { "model": "end_aspected:block/void_empty", "y": 180 }
    ]
  }
}